poynter.py
poynter-0.0.3.dist-info/LICENSE
poynter-0.0.3.dist-info/METADATA
poynter-0.0.3.dist-info/WHEEL
poynter-0.0.3.dist-info/top_level.txt
poynter-0.0.3.dist-info/RECORD
