Metadata-Version: 2.1
Name: poynter
Version: 0.0.3
Summary: Library for experiencing C hell in python
Author: Aron Heck
License: UNKNOWN
Platform: UNKNOWN
Classifier: Programming Language :: Python :: 3
Classifier: License :: OSI Approved :: MIT License
Classifier: Operating System :: OS Independent
Requires-Python: >=3.6
License-File: LICENSE
